{
    "nikaya": "විමානවත්ථු",
    "vagga": "තතිය නාවා විමාන වත්ථු",
    "sutta_title": "තුන්වෙනි නාවා විමානය",
    "id": "13022",
    "discovery_content": {
        "is_deep_meaning_found": true,
        "theme_category": "කර්ම විපාක සහ පරිත්‍යාගශීලිත්වය (Kamma and Generosity)",
        "complexity_rating": 3,
        "analysis_confidence": 95,
        "short_summary": "භික්ෂූන් වහන්සේලාගේ පිපාසය සංසිඳුවීමට පැන් පූජා කිරීමේ පිනෙන්, රන්වන් යානා සහ දිව්‍ය සම්පත් ලැබූ දේවතාවියකගේ පුවතකි.",
        "long_summary": "මනුෂ්‍ය ලෝකයේදී පිපාසයෙන් පීඩා විඳිමින් සිටි භික්ෂූන් වහන්සේලා පිරිසක් දැක, වහා නැගී සිට තම ශක්ති ප්‍රමාණයෙන් පැන් පූජා කළ කාන්තාවක්, එම කුසල කර්මයේ විපාක ලෙස දිව්‍ය ලෝකයේ උපත ලබා ඇත. ඇය රන්වන් වහල සහිත යානයක වැඩවසන, නෙළුම් මල් පිරි පොකුණු හා පලතුරු වනයන්ගෙන් පිරි, අතිශය ආලෝකවත් සිරුරක් ඇති දේවතාවියක් බවට පත්වූ බව බුදුරජාණන් වහන්සේට පවසයි. සිතේ උපන් අචල ප්‍රසාදය හා කරුණාව මෙවන් මහා විපාක ගෙන දීමට හේතු වූ බව මෙහි අවධාරණය කෙරේ.",
        "main_discovery": "අතිශය පිපාසිතව සිටි පිරිසකට පිරිසිදු ජලය පූජා කිරීම වැනි සරල නමුත් කරුණාවෙන් පිරි ක්‍රියාවක්, චිත්ත ප්‍රසාදය හරහා අතිමහත් ආනිශංස ගෙන දෙන ආකාරය මෙහි දැක්වේ.",
        "core_truth_of_sutta": "චේතනාන්විතව සිදුකරන කුඩා හෝ පරිත්‍යාගයක්, චිත්ත ප්‍රසාදයේ බලපෑම මත අතිවිශාල සැප විපාක ගෙන දෙයි.",
        "path_to_nibbana": {
            "doctrinal_meaning": "දානමය කුසලය (Generosity as Merit)",
            "how_it_aids_liberation": "ලෝභය (Greed) දුරු කිරීම සහ අත්හැරීම පුහුණු කිරීම මගින් සිතේ බැඳීම් ලිහිල් කර නිවනට මග පාදයි.",
            "practical_renunciation": "තමා සතු දෙය අනෙකාගේ යහපත උදෙසා කැප කිරීම මගින් 'මම' සහ 'මගේ' යන මමත්වය බැහැර කිරීම."
        },
        "psychological_analysis": {
            "mental_states_analyzed": [
                "කරුණාව (Compassion)",
                "ත්‍යාගශීලී බව (Generosity)",
                "ප්‍රීතිය (Priti)"
            ],
            "cognitive_impact": "පරාර්ථකාමීත්වය (Altruism) මගින් ආත්ම-කේන්ද්‍රීය සිතුවිලි (Self-centered thoughts) පලවා හැර මානසික සුවතාවය ඇති කරයි.",
            "modern_psychology_parallel": "Altruistic Behavioral Therapy - අනුන්ට උදවු කිරීම හරහා මානසික අවපීඩනය සහ ආතතිය කළමනාකරණය කිරීම."
        },
        "neuroscientific_analysis": {
            "brain_networks_involved": [
                "Reward System (Ventral Striatum)",
                "Oxytocin System",
                "Prefrontal Cortex (PFC)"
            ],
            "neuroplasticity_and_habit": "පරිත්‍යාගය පුරුදු කිරීමෙන් මොළයේ ඩොපමින් (Dopamine) මුදාහැරෙන ස්නායු මාර්ග ශක්තිමත් වී, සහකම්පනය ස්වයංක්‍රීය පුරුද්දක් බවට පත්වේ (Neuroplasticity).",
            "stress_reduction_mechanism": "අනුන්ගේ දුක දැක එය නිවීමට ක්‍රියා කිරීමේදී ඇමිග්ඩලා (Amygdala) මගින් පාලනය වන බිය සහ ආතතිය අඩු වී ඔක්සිටොසින් (Oxytocin) මට්ටම ඉහළ යයි."
        },
        "cognitive_mechanisms": [
            "සංවේදනය (Empathy)",
            "සතුටු සහගත චිත්තවේග (Positive Affect)",
            "කෘතවේදීත්වය (Gratitude)",
            "පරිත්‍යාගශීලී චේතනාව (Altruistic Intention)"
        ],
        "emotional_tone": {
            "primary_emotion": "ප්‍රීතිය (Joy)",
            "emotional_intensity": 8,
            "emotional_arc": "පිපාසය නිසා ඇති වූ අනුකම්පාවෙන් ආරම්භ වී, පරිත්‍යාගයේ තෘප්තිය හරහා දිව්‍යමය ප්‍රමෝදය දක්වා ගමන් කරයි.",
            "mood_keywords": [
                "ප්‍රසාදය",
                "ශාන්තිය",
                "ප්‍රභාස්වර",
                "කෘතඥතාව"
            ]
        },
        "scientific_parallels": [
            {
                "field": "Positive Psychology",
                "theory_name": "Helper's High",
                "parallel_description": "අනුන්ට උපකාර කිරීමේදී ලැබෙන මානසික තෘප්තිය සහ ශාරීරික සුවතාවය මෙහි දිව්‍ය සැප සම්පත් ලෙස සංකේතවත් වේ.",
                "confidence_score": 90
            }
        ],
        "sutta_connections": [
            {
                "shared_concept": "දානමය පින (Merit of Giving)",
                "related_teachings": [
                    "දාන සූත්‍රය",
                    "දක්ඛිණවිභංග සූත්‍රය"
                ],
                "connection_type": "දානයේ විපාක විස්තර කිරීම"
            }
        ],
        "practical_takeaway_sinhala": "කුඩා හෝ පරිත්‍යාගයක් අවංක කරුණාවෙන් යුතුව කිරීම, තමාට මෙන්ම අනෙකාටද දීර්ඝකාලීන මානසික සුවය ගෙන දෙයි.",
        "daily_practice_steps": [
            "අවට සිටින පිපාසිත හෝ පීඩිත සතෙකුට/පුද්ගලයෙකුට උදවු කිරීමට දිනපතා අවස්ථාවක් සොයාගන්න.",
            "පරිත්‍යාගය කරන මොහොතේදී එම සතුට සිතින් විඳින්න (Joyful giving).",
            "කරන ලද කුසල ක්‍රියාව රාත්‍රී නින්දට පෙර නැවත සිහිපත් කරමින් චිත්ත ප්‍රසාදය ඇති කරගන්න (Cittanussati)."
        ]
    },
    "content": [
        {
            "pali": "සුවණ්ණච්ඡදනං නාවං නාරී ආරුය්හ තිට්ඨසි,\nඕගාහසි පොක්ඛරණිං පදුමං ඡින්දසි පාණිනා",
            "sinhala": "“පින්වත් දෙව්දුව, රත්තරනින් නිම කළ ලස්සන වහලක් ඇති නැවකයි ඔබ ඉන්නේ. දිව්‍ය වූ නෙළුම් මල් පිපුණ පොකුණට බැහැලා අතින් නෙළුම් නෙලමින් නේද ඉන්නේ?"
        },
        {
            "pali": "කූටාගාරා නිවේසා තේ විභත්තා භාගසෝ මිතා,\nදද්දල්ලමානා ආභන්ති සමන්තා චතුරෝ දිසා",
            "sinhala": "ඒ ඔබේ දිව්‍ය විමානයේ සුවිශාල මන්දිර තියෙනවා. හරි අපූරුවට කාමර වශයෙන් බෙදලා තියෙනවා. හාත්පස සතර දිග්භාගයේම ඒ විමානය දිළිසෙනවා."
        },
        {
            "pali": "කේන තේ තාදිසෝ වණ්ණෝ කේන තේ ඉධමිජ්ඣති,\nඋප්පජ්ජන්ති ච තේ භෝගා යේ කේචි මනසෝ පියා",
            "sinhala": "ඇත්තෙන්ම ඔබට මෙවැනි ලස්සනක් ලැබුනේ කොහොමද? මොන වගේ පිනකින්ද ඔබට මේවා ලැබුනේ? සිතට ප්‍රිය උපදවන මේ සැප සම්පත් ලැබුනේ මොන වගේ පිනකින්ද?"
        },
        {
            "pali": "පුච්ඡාමි තං දේවි මහානුභාවේ\nමනුස්සභූතා කිමකාසි පුඤ්ඤං,\nකේනාසි ඒවං ජලිතානුභාවා\nවණ්ණෝ ච තේ සබ්බදිසා පභාසතීති",
            "sinhala": "මහානුභාව ඇති පින්වත් දෙව්දුව, මිනිස් ලෝකෙ ඉන්න කාලෙදී මොන වගේ පිනක්ද ඔබ කළේ? ආනුභාව සම්පන්නව ඔය බැබලි බැබලී ඉන්න පින මොකක්ද? ඔබේ සිරුරෙන් විහිදෙන එළියෙන් හැම දිශාවම බබලනවා."
        },
        {
            "pali": "සා දේවතා අත්තමනා සම්බුද්ධේනේව පුච්ඡිතා\nපඤ්හං පුට්ඨා වියාකාසි යස්ස කම්මස්සිදං ඵලන්ති",
            "sinhala": "සම්බුදුරජාණන් වහන්සේ තමයි මේ ප්‍රශ්න ඇහුවේ. ඒ ගැන ඒ දෙව්දුව ගොඩාක් සතුටු වුනා. මොන වගේ පින්කම්වලින්ද මේ සැප ලැබුනේ කියන ප්‍රශ්නයට ඇය මෙහෙමයි පිළිතුරු දුන්නේ."
        },
        {
            "pali": "අහං මනුස්සේසු මනුස්සභූතා\nපුරිමාය ජාතියා මනුස්සලෝකේ,\nදිස්වාන භික්ඛූ තසිතේ කිලන්තේ\nඋට්ඨාය පාතුං උදකං අදාසිං",
            "sinhala": "ඒ කලින් ජීවිතයේ මං හිටියේ මනුස්ස දුවක් වෙලා. එදා මං පිපාසයෙන් කලන්තේ හැදිලා වැටිල හිටිය ස්වාමීන් වහන්සේලා කිහිප නමක් දැක්කා. මං ඉක්මනට නැගිටලා උන්වහන්සේලාට වළඳන්න පැන් ටිකක් පූජා කරගත්තා."
        },
        {
            "pali": "යෝ වේ කිලන්තාන පිපාසිතානං\nඋට්ඨාය පාතුං උදකං දදාති,\nසීතෝදකා තස්ස භවන්ති නජ්ජෝ\nපහූතමාල්‍යා බහු පුණ්ඩරීකා",
            "sinhala": "ඉතින් කවුරු හරි කෙනෙක් පිපාසයෙන් කලන්තේ හැදිලා වැටිලා ඉන්න කෙනෙකුට ඉක්මනින්ම වළඳන්න පැන් ටිකක් දුන්නොත් ඒ කෙනාට සීතල දියදහර පිරී ගිය, ලස්සන මල් පිරුන, සුදු නෙලුම් පිපිලා තිබෙන ගංගාවන් පහළ වෙනවා."
        },
        {
            "pali": "තමාපගා අනුපරියන්ති සබ්බදා\nසීතෝදකා වාලු‍කසන්ථතා නදී,\nඅම්බා ච සාලා තිලකා ච ජම්බුයෝ\nඋද්දාලකා පාටලියෝ ච ඵුල්ලා",
            "sinhala": "එතකොට ඒ දිව්‍ය විමානය වටකරගෙන ලස්සන සුදු වැලි තලාව හැදෙනවා. ඒ මතින් තමයි සිහිල් දිය දහරා ඇති ලස්සන ගංගාවන් හැම තිස්සේම ගලාගෙන බසින්නේ. ඉතින් ඒ හැමතැනම මල් පිපුණු අඹ ගස් තියෙනවා. සල් ගස් තියෙනවා. තිලක ගස් තියෙනවා. දඹ ගස් තියෙනවා. ඇහැල ගස් තියෙනවා. පලොල් ගසුත් තියෙනවා."
        },
        {
            "pali": "තං භූමිභාගේහි උපේතරූපං\nවිමානසෙට්ඨං භුසසෝභමානං,\nතස්සීධ කම්මස්ස අයං විපාකෝ\nඒතාදිසං කතපුඤ්ඤා ලභන්ති",
            "sinhala": "එවැනි බිම් පෙදෙස්වල තමයි දිව්‍ය විමාන පහළ වෙන්නේ. ඒ දිව්‍ය විමාන පුදුම විදිහේ සුන්දරත්වයෙන් යුක්තයි. ඉතින් ස්වාමීනී, එදා මා කළ ඒ පින්කමින් තමයි මේ විපාකය ලැබුනේ. පින්කළ අයට තමයි මේ වගේ සම්පත් ලැබෙන්නේ."
        },
        {
            "pali": "කූටාගාරා නිවේසා මේ විභත්තා භාගසෝ මිතා,\nදද්දල්ලමානා ආභන්ති සමන්තා චතුරෝ දිසා",
            "sinhala": "ඒ මගේ දිව්‍ය විමානයේ සුවිශාල මන්දිර තියෙනවා. හරි අපූරුවට කාමර බෙදලා තියෙනවා. හාත්පස සතර දිග්භාගයේම ඒ විමානය දිළිසෙනවා."
        },
        {
            "pali": "තේන මේ තාදිසෝ වණ්ණෝ තේන මේ ඉධමිජ්ඣති,\nඋප්පජ්ජන්ති ච මේ භෝගා යේ කේචි මනසෝ පියා",
            "sinhala": "ඒ පිනෙන් තමයි මෙවැනි ලස්සනක් මට ලැබුනේ. ඒ පිනෙන්මයි මේ සම්පත් ලැබුනේ. සිතට ප්‍රීතිය උපදවන මේ සැප සම්පත් ඔක්කොම ලැබුනේ ඒ නිසාමයි."
        },
        {
            "pali": "තේනම්හි ඒවං ජලිතානුභාවා\nවණ්ණෝ ච මේ සබ්බදිසා පභාසති,\nඒතස්ස කම්මස්ස ඵලං මමේදං\nඅත්ථාය බුද්ධෝ උදකං අපායීති",
            "sinhala": "මහානුභාව සම්පන්න වූ ස්වාමීන් වහන්ස, මිනිස් ලෝකෙදී ඔය පින තමයි මං කරගත්තේ. ආනුභාව සම්පන්නව බැබළි බැබළී ඉන්න පින ඕක තමයි. මගේ සිරුරෙන් විහිදෙන එළියෙන් හැම දිශාවම බබලනවා."
        }
    ]
}