{
    "nikaya": "මහා වග්ගෝ",
    "vagga": "පරිසුද්ධ සුත්තං",
    "sutta_title": "පිරිසිදු නිවන් මග ගැන වදාළ දෙසුම",
    "id": "3110",
    "discovery_content": {
        "is_deep_meaning_found": true,
        "theme_category": "ආර්ය අෂ්ටාංගික මාර්ගය (The Noble Eightfold Path)",
        "complexity_rating": 4,
        "analysis_confidence": 95,
        "short_summary": "බුදුරජාණන් වහන්සේගේ පහළ වීමත් සමඟම ලොවට විවෘත වන, කෙලෙස්වලින් තොර වූ පිරිසිදු මාර්ගාංග අටක ස්වභාවය මෙහි විස්තර කෙරේ.",
        "long_summary": "සැවැත් නුවරදී දේශනා කරන ලද මෙම සූත්‍රය මගින් සම්මා දිට්ඨිය සහ සම්මා සමාධිය ඇතුළු අසමෝෂ්ඨ ධර්ම අටක් පිළිබඳව විවරණය කරයි. මෙම ධර්ම පද්ධතිය පිරිසිදු වූත්, කෙලෙස්වලින් තොර වූත්, උපක්ලේශවලින් විනිර්මුක්ත වූත් ස්වභාවයකින් යුක්ත වේ. තථාගතයන් වහන්සේ නමකගේ පහළ වීමෙන් තොරව අන් කිසිදු කාලයක මෙම ධර්ම අට ලොව පහළ නොවන බවත්, මෙය නිර්මල නිවන් මගෙහි පදනම බවත් මෙහි අවධාරණය කෙරේ.",
        "main_discovery": "බුදුන් වහන්සේගේ පහළ වීමෙන් පමණක් ලොවට හෙළිවන, උපක්ලේශ රහිත නිර්මල විමුක්ති මාර්ගයේ පදනම වන මාර්ගාංග අටෙහි (Noble Eightfold Path Components) ඇති අසමසම පිරිසිදු බව හඳුනා ගැනීම.",
        "core_truth_of_sutta": "නිවන් මග යනු බාහිර ලෝකයෙන් සොයාගත නොහැකි, සම්මා සම්බුදුවරයෙකුගේ මගපෙන්වීම යටතේ සිත තුළ ඇති කරගන්නා උපක්ලේශ රහිත අභ්‍යන්තර පිරිසිදු වීමකි.",
        "path_to_nibbana": {
            "doctrinal_meaning": "සම්මා දිට්ඨියේ සිට සම්මා සමාධිය දක්වා වූ මාර්ගාංග කෙලෙස් රහිතව (Anupakkilesa) ප්‍රගුණ කිරීම.",
            "how_it_aids_liberation": "සිතේ ඇතිවන සියුම් කෙලෙස් (Upakkilesa) ඉවත් කිරීම මගින් විමුක්තිය සඳහා අවශ්‍ය මානසික පදනම සකස් කරයි.",
            "practical_renunciation": "වැරදි දැකීම් සහ අකුසල සහගත චින්තන රටාවන් ක්‍රමයෙන් අත්හැරීම (Letting go of cognitive biases)."
        },
        "psychological_analysis": {
            "mental_states_analyzed": [
                "නිරවුල් මනස (Mental Clarity)",
                "අකලංක අවධානය (Undistracted Attention)",
                "මෝහයෙන් තොර වීම (Lack of Delusion)"
            ],
            "cognitive_impact": "සම්මා දිට්ඨිය මගින් පක්ෂපාතීත්වයෙන් තොරව යථාර්ථය දැකීමේ හැකියාව (Metacognition) වර්ධනය කරයි.",
            "modern_psychology_parallel": "පිළිගැනීමේ සහ කැපවීමේ චිකිත්සාව (Acceptance and Commitment Therapy - ACT) මගින් සිදුකරන සිතුවිලිවලට ඇති ඇලීම පාලනය කිරීමේ ක්‍රියාවලියට සමාන වේ."
        },
        "neuroscientific_analysis": {
            "brain_networks_involved": [
                "Prefrontal Cortex (PFC)",
                "Anterior Cingulate Cortex (ACC)",
                "Default Mode Network (DMN)"
            ],
            "neuroplasticity_and_habit": "සම්මා සමාධිය පුහුණු කිරීමේදී DMN පද්ධතියේ ක්‍රියාකාරිත්වය අඩුවී, මොළය ස්වයං-විවේචනාත්මක සිතුවිලිවලින් මිදී වර්තමාන මොහොතට අවධානය යොමු කිරීමට හුරු වේ (Neuroplasticity).",
            "stress_reduction_mechanism": "සම්මා දිට්ඨිය හරහා ලෝකය දකින ආකාරය වෙනස් වීම නිසා Amygdala හි අධි-ක්‍රියාකාරීත්වය පාලනය වී Cortisol මට්ටම අඩු වේ."
        },
        "cognitive_mechanisms": [
            "සම්මා දිට්ඨිය (Right View)",
            "සම්මා සමාධිය (Right Concentration)",
            "ප්‍රජානන ප්‍රතිව්‍යුහගතකරණය (Cognitive Restructuring)",
            "උපක්ලේශ ප්‍රහාණය (Defilement Elimination)"
        ],
        "emotional_tone": {
            "primary_emotion": "ශ්‍රද්ධාව සහ ප්‍රසාදය (Serenity & Devotion)",
            "emotional_intensity": 8,
            "emotional_arc": "විමතියේ සිට නිසල මනසක් කරා (From Awe to Tranquility)",
            "mood_keywords": [
                "නිර්මලත්වය",
                "ප්‍රඥාව",
                "ශාන්තිය"
            ]
        },
        "scientific_parallels": [
            {
                "field": "Cognitive Science",
                "theory_name": "Cognitive Transformation Theory",
                "parallel_description": "සම්මා දිට්ඨිය මගින් ලෝකය දකින වැරදි දෘෂ්ටිකෝණ (Cognitive Distortions) නිවැරදි කරමින් මානසික නිරවුල්භාවය ඇති කිරීම.",
                "confidence_score": 90
            }
        ],
        "sutta_connections": [
            {
                "shared_concept": "ආර්ය අෂ්ටාංගික මාර්ගය",
                "related_teachings": [
                    "ධම්මචක්කප්පවත්තන සූත්‍රය",
                    "මහා සතිපට්ඨාන සූත්‍රය"
                ],
                "connection_type": "මූලික ධර්ම කරුණු අන්‍යෝන්‍ය වශයෙන් සහයෝගී වීම"
            }
        ],
        "practical_takeaway_sinhala": "ඔබේ දෛනික ගැටලුවලට හේතුව ලෝකය නොව, ඔබ ලෝකය දකින වැරදි ආකාරය (වැරදි දෘෂ්ටිය) බව වටහාගෙන සිත පිරිසිදු කරගැනීමට උත්සාහ කරන්න.",
        "daily_practice_steps": [
            "දවස ආරම්භයේදී ඔබ දරන මතයන් කොතරම් දුරට නිවැරදිදැයි ස්වයං-විවේචනයක යෙදෙන්න (Right View check).",
            "ඕනෑම කාර්යයකදී අවධානය විසිරී යාමට නොදී එක් අරමුණක තබා ගැනීමට උත්සාහ කරන්න (Right Concentration).",
            "සිතේ ඇතිවන කෝපය හෝ ආශාව වැනි උපක්ලේශ හඳුනාගෙන ඒවා ක්ෂණිකව ඉවත් කිරීමට පුරුදු වන්න."
        ]
    },
    "content": [
        {
            "pali": "සාවත්ථියං....",
            "sinhala": "සැවැත් නුවර දී ය ………"
        },
        {
            "pali": "අට්ඨිමේ භික්ඛවේ, ධම්මා පරිසුද්ධා පරියෝදාතා අනංගණා විගතූපක්කිලේසා අනුප්පන්නා උප්පජ්ජන්ති, නාඤ්ඤත්‍ර තථාගතස්ස පාතුභාවා අරහතෝ සම්මාසම්බුද්ධස්ස. කතමේ අට්ඨ: සෙය්‍යථිදං: සම්මාදිට්ඨි ....(පෙ).... සම්මාසමාධි. ඉමේ ඛෝ භික්ඛවේ, අට්ඨධම්මා පරිසුද්ධා පරියෝදාතා අනංගණා විගතූපක්කිලේසා අනුප්පන්නා උප්පජ්ජන්ති, නාඤ්ඤත්‍ර තථාගතස්ස පාතුභාවා අරහතෝ සම්මාසම්බුද්ධස්සාති.",
            "sinhala": "මහණෙනි, පිරිසිදු ව බබලන්නා වූ, කෙලෙස් රහිත වූ, උපක්ලේශ රහිත වූ මේ ධර්මයන් අට තථාගත අරහත් සම්මා සම්බුදුරජාණන් වහන්සේගේ පහළ වීමෙන් විනා අන් කාලයක ඇති නොවූ ත්, අන් කාලයක ඇති නොවන්නා වූ ත් දෙයකි. ඒ කවර ධර්ම අටක් ද යත්, එනම්; සම්මා දිට්ඨිය ….(පෙ)…. සම්මා සමාධිය යි. මහණෙනි, පිරිසිදු ව බබලන්නා වූ, කෙලෙස් රහිත වූ, උපක්ලේශ රහිත වූ මේ ධර්මයන් අට තථාගත අරහත් සම්මා සම්බුදුරජාණන් වහන්සේගේ පහළ වීමෙන් විනා අන් කාලයක ඇති නොවූ ත්, අන් කාලයක ඇති නොවන්නා වූ ත් දෙයකි."
        }
    ]
}