{
    "nikaya": "මහා වග්ගෝ",
    "vagga": "දුතිය සමුද්දනින්න සුත්තං",
    "sutta_title": "සමුද්‍රයට නැමී තිබීම ගැන වදාළ දෙවෙනි දෙසුම",
    "id": "4666",
    "discovery_content": {
        "is_deep_meaning_found": true,
        "theme_category": "සම්මා සමාධි සහ මාර්ග ප්‍රගුණ කිරීම (Path Cultivation)",
        "complexity_rating": 3,
        "analysis_confidence": 100,
        "short_summary": "යමුනා නදිය මුහුදටම නැඹුරු වී ගලා බසින්නාක් මෙන්, නිවන අරමුණු කරන ශ්‍රාවකයා තම මුළු චිත්ත සන්තානයම නිවනටම නැඹුරු කරගත යුතුය.",
        "long_summary": "යමුනා නදිය ස්වභාවිකවම මුහුද දෙසට නැමී, මුහුද දෙසට බෑවුම් වී, මුහුද දෙසටම බර වී ගලා යන්නාක් මෙන්, නිවන සාක්ෂාත් කර ගැනීමට උත්සාහ කරන භික්ෂුව හෝ ශ්‍රාවකයාද තමන්ගේ සම්පූර්ණ මානසික අවධානය සහ උත්සාහය නිවන කෙරෙහිම නැඹුරු කළ යුතු බවත්, නිවන කෙරෙහිම බර විය යුතු බවත් මෙම දේශනාවේ සඳහන් වේ.",
        "main_discovery": "මානසික අවධානය සහ අභිප්‍රාය (Intentionality) නිශ්චිත ඉලක්කයක් වෙත යොමු කිරීමෙන් ස්වයංක්‍රීයවම විමුක්තිය කරා ගලා යාම.",
        "core_truth_of_sutta": "විමුක්තිය උදෙසා සිතේ පවත්නා අඛණ්ඩ නැඹුරුව සහ කැපවීම සාර්ථකත්වයේ පදනමයි.",
        "path_to_nibbana": {
            "doctrinal_meaning": "නිවන කෙරෙහි ඇති කරන 'අධිමුක්තිය' (Commitment) සහ 'විවේක නිස්සිත' (Relied on Seclusion) මානසිකත්වය.",
            "how_it_aids_liberation": "සිත සංසාරික අරමුණු වලින් ඉවත් වී විරාගය සහ නිරෝධය වෙත ස්වයංක්‍රීයවම යොමු වීමට මග පාදයි.",
            "practical_renunciation": "ලෞකික බැඳීම් වලින් සිත ක්‍රමයෙන් මුදාගෙන අත්හැරීමේ (Nekkhamma) සුවය දෙසට සිත යොමු කිරීම."
        },
        "psychological_analysis": {
            "mental_states_analyzed": [
                "අරමුණක පිහිටීම (One-pointedness)",
                "අධිෂ්ඨානය (Determination)"
            ],
            "cognitive_impact": "සිතේ විසිරුණු ස්වභාවය (Cognitive Dissonance) පාලනය කර එක් මාවතක ගලා යාමට සිත හැඩගැස්වීම.",
            "modern_psychology_parallel": "පිළිගැනීමේ සහ කැපවීමේ ප්‍රතිකාරය (Acceptance and Commitment Therapy - ACT) තුළ ඇති අගයයන් කෙරෙහි නැඹුරු වීමේ (Values-based action) සංකල්පයට සමානය."
        },
        "neuroscientific_analysis": {
            "brain_networks_involved": [
                "Default Mode Network (DMN)",
                "Executive Control Network (ECN)"
            ],
            "neuroplasticity_and_habit": "නැවත නැවතත් නිවන අරමුණු කිරීමෙන් ස්නායු පථ (Neural pathways) ශක්තිමත් වී සිත ඉබේම එම දිශාවට යොමුවන 'Hebbian Learning' ක්‍රියාවලිය සිදුවේ.",
            "stress_reduction_mechanism": "නිශ්චිත ඉලක්කයක් (නිවන) කෙරෙහි සිත බර කිරීම නිසා Amygdala හි අනවශ්‍ය උද්වේගකර බව අඩු වී පූර්ව ප්‍රශ්චාත් මස්තිෂ්ක බාහිකයේ (Prefrontal Cortex) පාලනය ස්ථාපිත වේ."
        },
        "cognitive_mechanisms": [
            "චේතනාන්විත නැඹුරුව (Intentional Orientation)",
            "සංජානන ඉලක්කගතකරණය (Cognitive Targeting)",
            "අඛණ්ඩ පුහුණුව (Continuous Reinforcement)"
        ],
        "emotional_tone": {
            "primary_emotion": "සන්සුන් බව (Equanimity)",
            "emotional_intensity": 7,
            "emotional_arc": "විසිරුණු බවේ සිට ඒකාග්‍රතාවය දක්වා (Scatter to Focus)",
            "mood_keywords": [
                "නොසැලෙන",
                "ගලායන",
                "අකම්පිත"
            ]
        },
        "scientific_parallels": [
            {
                "field": "චර්යාත්මක මනෝවිද්‍යාව (Behavioral Psychology)",
                "theory_name": "නියත නැඹුරුව (Priming/Intentionality)",
                "parallel_description": "යම් ඉලක්කයක් කෙරෙහි සිත නැවත නැවතත් නැඹුරු කිරීමේදී එම ඉලක්කයට අදාළ උත්තේජනයන්ට ප්‍රතිචාර දැක්වීමේ සම්භාවිතාව වැඩිවීම.",
                "confidence_score": 90
            }
        ],
        "sutta_connections": [
            {
                "shared_concept": "නැඹුරු බව (Inclination)",
                "related_teachings": [
                    "සම්මා සංකප්ප (Right Resolve)",
                    "ඉන්ද්‍රිය භාවනා සූත්‍රය"
                ],
                "connection_type": "මාර්ගයේ ස්වභාවය විස්තර කිරීම"
            }
        ],
        "practical_takeaway_sinhala": "ඔබේ දෛනික කටයුතු අතරතුර පවා සිතේ ගැඹුරු අරමුණ අත්නොහැර නිවන කෙරෙහි නැඹුරු වී සිටින්න.",
        "daily_practice_steps": [
            "උදෑසන අවදි වූ සැණින් අද දවස තුළ අත්හැරීම සහ සන්සුන් බව පුහුණු කරන බවට අධිෂ්ඨානය කරන්න.",
            "යම් ගැටුමක් හෝ ආශාවක් ඇති වූ විට 'මෙය මා නිවනට ගෙන යනවාද?' යන්න විමසන්න.",
            "සෑම ක්‍රියාවකදීම ගංගාවක් මුහුදට ගලා යන්නාක් මෙන් සිතේ සන්සුන් බව පවත්වා ගන්න."
        ]
    },
    "content": [
        {
            "pali": "සෙය්‍යථාපි භික්ඛවේ, යමුනා නදී සමුද්දනින්නා සමුද්දපෝණා සමුද්දපබ්භාරා. ඒවමේව ඛෝ භික්ඛවේ, භික්ඛු ....(පෙ).... නිබ්බානපබ්භාරෝති.",
            "sinhala": "මහණෙනි, යමුනා නදිය සමුද්‍රයට නැමී, සමුද්‍රයට නැඹුරු වී, සමුද්‍රයට බර වී ඇත්තේ යම් සේ ද, එසෙයින් ම මහණෙනි, භික්ෂුවක් ….(පෙ)…. නිවනට බර වූයේ වෙයි."
        }
    ]
}