{
    "nikaya": "සළායතන වග්ගෝ",
    "vagga": "නිබ්බාන සුත්තං",
    "sutta_title": "නිවන ගැන වදාළ දෙසුම",
    "id": "5358",
    "discovery_content": {
        "is_deep_meaning_found": true,
        "theme_category": "Soteriology / Cognitive Transformation",
        "complexity_rating": 4,
        "analysis_confidence": 100,
        "short_summary": "නිවන යනු රාග, ද්වේෂ, මෝහයන්ගේ ක්ෂය වීම බවත්, එය සාක්ෂාත් කිරීමේ එකම මග ආර්ය අෂ්ටාංගික මාර්ගය බවත් සාරිපුත්ත රහතන් වහන්සේ පැහැදිලි කරති.",
        "long_summary": "මගධයේ නාල ගමේදී සාරිපුත්තයන් වහන්සේ හමු වූ ජම්බුඛාදක පිරිවැජියා නිවන සහ එයට මග විමසයි. එහිදී සාරිපුත්තයන් වහන්සේ පෙන්වා දෙන්නේ රාග, ද්වේෂ සහ මෝහ යන අකුසල මූලයන් සම්පූර්ණයෙන්ම ක්ෂය වීම නිවන බවයි. මෙම තත්ත්වය අත්පත් කර ගැනීම සඳහා සම්මා දිට්ඨියේ සිට සම්මා සමාධිය දක්වා වූ අංග අටකින් යුත් ආර්ය අෂ්ටාංගික මාර්ගය ප්‍රායෝගිකව අනුගමනය කළ යුතු එකම ප්‍රතිපදාව ලෙස උන්වහන්සේ දේශනා කරති.",
        "main_discovery": "නිවන යනු රාග, ද්වේෂ, මෝහයන්ගෙන් තොර වූ මානසික නිදහස වන අතර එය ආර්ය අෂ්ටාංගික මාර්ගය තුළින් අත්පත් කරගත හැකි බව.",
        "core_truth_of_sutta": "නිවන යනු තණ්හාව හා ද්වේෂය මුල් වූ චිත්තවේගීය බැඳීම් සහ මෝහය මුල් වූ අවිද්‍යාව ප්‍රහීණ කිරීමයි.",
        "path_to_nibbana": {
            "doctrinal_meaning": "නිවන යනු සිතේ ඇති වන රාග, ද්වේෂ සහ මෝහ යන සංස්කාරයන්ගේ (Sankhara) අවසානයයි.",
            "how_it_aids_liberation": "ආර්ය අෂ්ටාංගික මාර්ගය ඔස්සේ සීල, සමාධි, ප්‍රඥා ගොඩනැගීමෙන් සිතේ පවත්නා කෙලෙස් බීජ විනාශ වී විමුක්තිය උදා වේ.",
            "practical_renunciation": "රාගය පවතින තැන අශුභයත්, ද්වේෂය පවතින තැන මෙත්තාවත් වර්ධනය කරමින් ක්ලේශයන්ගේ ග්‍රහණයෙන් මිදීම."
        },
        "psychological_analysis": {
            "mental_states_analyzed": [
                "රාගය (Attachment/Lust)",
                "ද්වේෂය (Aversion/Anger)",
                "මෝහය (Delusion/Ignorance)"
            ],
            "cognitive_impact": "සම්මා දිට්ඨිය මගින් ලෝකය දකින විකෘති දැක්ම (Cognitive Distortions) ඉවත් කර යථාර්ථවාදී දැක්මක් ලබා දෙයි.",
            "modern_psychology_parallel": "අංග අටකින් යුත් මෙම ක්‍රමවේදය ACT (Acceptance and Commitment Therapy) හි අගයන් මත පදනම් වූ ක්‍රියාකාරීත්වයට බෙහෙවින් සමානය."
        },
        "neuroscientific_analysis": {
            "brain_networks_involved": [
                "Default Mode Network (DMN)",
                "Amygdala",
                "Prefrontal Cortex (PFC)"
            ],
            "neuroplasticity_and_habit": "සම්මා වායාමය සහ සම්මා සතිය මගින් පරණ අකුසල සහගත ස්නායුක රටා (Habitual neural pathways) දුර්වල කර, නව කුසල සහගත රටා ශක්තිමත් කරයි (Neuroplasticity).",
            "stress_reduction_mechanism": "සම්මා සමාධිය මගින් Amygdala හි ක්‍රියාකාරීත්වය (ප්‍රතික්‍රියාශීලී බව) අඩු කර, Prefrontal Cortex හි පාලනය වර්ධනය කරමින් මානසික ආතතිය අවම කරයි."
        },
        "cognitive_mechanisms": [
            "Cognitive Restructuring",
            "Attentional Control",
            "Value Alignment",
            "Emotional Regulation"
        ],
        "emotional_tone": {
            "primary_emotion": "Equanimity (උපේක්ෂාව)",
            "emotional_intensity": 8,
            "emotional_arc": "විමසීමේ සිට පරම ශාන්තිය හා පැහැදීම දක්වා.",
            "mood_keywords": [
                "Clarity",
                "Peace",
                "Insightful",
                "Disciplined"
            ]
        },
        "scientific_parallels": [
            {
                "field": "Clinical Psychology",
                "theory_name": "Cognitive Behavioral Therapy (CBT)",
                "parallel_description": "සම්මා දිට්ඨිය සහ සම්මා සංකල්පය හරහා වැරදි සහගත විශ්වාස පද්ධති (Maladaptive schemas) නිවැරදි කිරීමේ ක්‍රියාවලියට සමාන වේ.",
                "confidence_score": 90
            }
        ],
        "sutta_connections": [
            {
                "shared_concept": "Nirvana as the cessation of defilements",
                "related_teachings": [
                    "Samyutta Nikaya 38.1"
                ],
                "connection_type": "Direct Definition"
            }
        ],
        "practical_takeaway_sinhala": "ඔබේ දෛනික තීරණ සහ සිතුවිලි ආර්ය අෂ්ටාංගික මාර්ගයට අනුකූලදැයි නිරීක්ෂණය කිරීමෙන් මානසික නොසන්සුන්බව පාලනය කර ගත හැක.",
        "daily_practice_steps": [
            "දවස ආරම්භයේදී අවම වශයෙන් විනාඩි 10ක් සම්මා සතිය (Mindfulness) පුහුණු කරන්න.",
            "ඕනෑම ක්‍රියාවකදී එය රාගයෙන් හෝ ද්වේෂයෙන් මෙහෙයවෙන්නේ දැයි ස්වයං විමර්ශනයක යෙදෙන්න.",
            "තමා පවසන වචන 'සම්මා වාචාව' ට අනුකූලදැයි (සත්‍යවාදී සහ ප්‍රියමනාප දැයි) සැලකිලිමත් වන්න."
        ]
    },
    "content": [
        {
            "pali": "ඒකං සමයං ආයස්මා සාරිපුත්තෝ මගධේසු විහරති නාලගාමකේ. අථ ඛෝ ජම්බුඛාදකෝ පරිබ්බාජකෝ යේනායස්මා සාරිපුත්තෝ තේනුපසංකමි. උපසංකමිත්වා ආයස්මතා සාරිපුත්තේන සද්ධිං සම්මෝදි. සම්මෝදනීයං කථං සාරාණීයං වීතිසාරෙත්වා ඒකමන්තං නිසීදි. ඒකමන්තං නිසින්නෝ ඛෝ ජම්බුඛාදකෝ පරිබ්බාජකෝ ආයස්මන්තං සාරිපුත්තං ඒතදවෝච: නිබ්බානං නිබ්බානන්ති ආවුසෝ සාරිපුත්ත වුච්චති. කතමන්නු ඛෝ ආවුසෝ නිබ්බානන්ති.",
            "sinhala": "ඒ දිනවල ආයුෂ්මත් සාරිපුත්තයන් වහන්සේ වැඩසිටියේ මගධ ජනපදයේ නාල නම් ගමේ. එදා ජම්බුඛාදක පිරිවැජියා ආයුෂ්මත් සාරිපුත්තයන් වහන්සේ වැඩසිටි තැනට ආවා. ඇවිදින් ආයුෂ්මත් සාරිපුත්තයන් වහන්සේ සමඟ සතුටු වුණා. සතුටු විය යුතු පිළිසඳර කථාබහේ යෙදිලා එකත්පස්ව වාඩිවුණා. එකත්පස්ව වාඩිවුණ ජම්බුඛාදක පිරිවැජියා ආයුෂ්මත් සාරිපුත්තයන් වහන්සේගෙන් මෙකරුණ විමසුවා. “ප්‍රිය ආයුෂ්මත් සාරිපුත්තයෙනි, නිවන, නිවන කියලා කියනවා. ප්‍රිය ආයුෂ්මතුනි, නිවන කියලා කියන්නේ කුමක්ද?”"
        },
        {
            "pali": "යෝ ඛෝ ආවුසෝ රාගක්ඛයෝ දෝසක්ඛයෝ මෝහක්ඛයෝ ඉදං වුච්චති නිබ්බානන්ති. අත්ථි පනාවුසෝ මග්ගෝ අත්ථි පටිපදා ඒතස්ස නිබ්බානස්ස සච්ඡිකිරියායාති. අත්ථි ඛෝ ආවුසෝ මග්ගෝ අත්ථි පටිපදා ඒතස්ස නිබ්බානස්ස සච්ඡිකිරියායාති. කතමෝ පනාවුසෝ මග්ගෝ කතමා පටිපදා ඒතස්ස නිබ්බානස්ස සච්ඡිකිරියායාති. අයමේව ඛෝ ආවුසෝ අරියෝ අට්ඨංගිකෝ මග්ගෝ ඒතස්ස නිබ්බානස්ස සච්ඡිකිරියාය, සෙය්‍යථිදං: සම්මාදිට්ඨි සම්මාසංකප්පෝ සම්මාවාචා සම්මාකම්මන්තෝ සම්මාආජීවෝ සම්මාවායාමෝ සම්මාසති සම්මාසමාධි. අයං ඛෝ ආවුසෝ මග්ගෝ අයං පටිපදා ඒතස්ස නිබ්බානස්ස සච්ඡිකිරියායාති. භද්දකෝ ආවුසෝ මග්ගෝ භද්දිකා පටිපදා ඒතස්ස නිබ්බානස්ස සච්ඡිකිරියාය. අලඤ්ච පනාවුසෝ සාරිපුත්ත, අප්පමාදායාති.",
            "sinhala": "“ආයුෂ්මත, යම් රාගය ක්‍ෂය වීමක්, ද්වේෂය ක්‍ෂය වීමක්, මෝහය ක්‍ෂය වීමක් ඇද්ද නිවන කියන්නේ මෙයටයි.” “ප්‍රිය ආයුෂ්මතුනි, ඔය නිවන සාක්‍ෂාත් කිරීම පිණිස වැඩපිළිවෙලක් තියෙනවාද? මාර්ගයක් තියෙනවාද?” “ආයුෂ්මත, මේ නිවන සාක්‍ෂාත් කිරීම පිණිස වැඩපිළිවෙළක් තියෙනවා. මාර්ගයකුත් තියෙනවා.” “ප්‍රිය ආයුෂ්මතුනි, ඔය නිවන සාක්‍ෂාත් කිරීම පිණිස පවතින වැඩපිළිවෙළ කුමක්ද? මාර්ගය කුමක්ද?” “ආයුෂ්මත, මේ නිවන සාක්‍ෂාත් කිරීම පිණිස පවතින්නේ ඒ මේ ආර්ය ආෂ්ටාංගික මාර්ගය ම යි. ඒ කියන්නේ; සම්මා දිට්ඨි, සම්මා සංකල්ප, සම්මා වාචා, සම්මා කම්මන්ත, සම්මා ආජීව, සම්මා වායාම, සම්මා සති, සම්මා සමාධි යන මෙයයි. ආයුෂ්මත, මේ නිවන සාක්‍ෂාත් කිරීම පිණිස තිබෙන්නේ ඔය මාර්ගය තමයි. ඔය ප්‍රතිපදාව තමයි.” “ප්‍රිය ආයුෂ්මතුනි, මේ නිවන සාක්‍ෂාත් කිරීම පිණිස පවතින්නේ සොඳුරු මඟක් ම යි. සොඳුරු ප්‍රතිපදාවක් ම යි. ප්‍රිය ආයුෂ්මත් සාරිපුත්තයෙනි, අප්‍රමාදී වීමට ම යි සුදුසු.”"
        }
    ]
}