{
    "nikaya": "සළායතන වග්ගෝ",
    "vagga": "කාමභූ සුත්තං",
    "sutta_title": "කාමභූ තෙරුන් නැගූ ප්‍රශ්න පිළිබඳ දෙසුම",
    "id": "5517",
    "discovery_content": {
        "is_deep_meaning_found": true,
        "theme_category": "සංකේතාත්මක ධර්ම විශ්ලේෂණය (Metaphorical Dhamma Analysis)",
        "complexity_rating": 4,
        "analysis_confidence": 5,
        "short_summary": "චිත්ත ගෘහපතිතුමා විසින් රථයක උපමාව ඇසුරින් මිනිස් සිරුරේ අනිත්‍ය බවත්, ශීලය, සතිය සහ නිවනේ ස්වභාවයත් මනාව විග්‍රහ කරන සූත්‍රයකි.",
        "long_summary": "මච්ඡිකාසණ්ඩයේදී චිත්ත ගෘහපතිතුමා කාමභූ තෙරුන් හමුවී, බුදුන් වහන්සේ දේශනා කළ රථයක උපමාවක් විග්‍රහ කරයි. මෙහිදී ශරීරය රථය ලෙසත්, ශීලය එහි පිරිසිදු බව (දොස් රහිත) ලෙසත්, සතිය එක් දැවිය ලෙසත්, විමුක්තිය සුදු වැස්ම ලෙසත් අර්ථ දක්වයි. රාග, ද්වේෂ, මෝහ යන බැඳීම්වලින් නිදහස් වූ, තණ්හාව සිඳ දැමූ අරහත් උත්තමයා නැවත උප්පත්තියක් කරා නොයන බවත්, සියලු දුක් නිවා ඇති බවත් මෙහි සවිස්තරව දැක්වේ.",
        "main_discovery": "භෞතික ශරීරය සහ මානසික අවබෝධය රථයක උපමාවෙන් විග්‍රහ කරමින්, රහත් භාවය දක්වා වූ ගමන විස්තර කිරීම.",
        "core_truth_of_sutta": "ප්‍රඥාව මගින් සිරුරේ අනිත්‍යතාව සහ කෙලෙස්වලින් මිදීම හඳුනා ගැනීම විමුක්තියට මගයි.",
        "path_to_nibbana": {
            "doctrinal_meaning": "ක්ෂීණාශ්‍රවත්වය (Arahantship) සහ තණ්හාව සිඳලීම (Elimination of Craving).",
            "how_it_aids_liberation": "සිරුරේ සතර මහා භූත ස්වභාවය වටහාගෙන කෙලෙස් බැඳුම් (Fetters) ප්‍රහීණ කිරීමෙන් පුනර්භවය වැළැක්වීම.",
            "practical_renunciation": "රාග, ද්වේෂ සහ මෝහ යන අගතිගාමී බැඳීම් අත්හැරීම සහ තණ්හාව නමැති සැඩපහර (Craving current) සිඳලීම."
        },
        "psychological_analysis": {
            "mental_states_analyzed": [
                "සති (Attention/Awareness)",
                "අබන්ධන (Freedom from Attachment)",
                "අනීඝ (Freedom from Suffering)"
            ],
            "cognitive_impact": "සිරුර 'මම' ලෙස නොව, අනිත්‍ය කොටස්වල එකතුවක් ලෙස දකින විභජ්‍යවාදී චින්තනයක් ගොඩනැගීම.",
            "modern_psychology_parallel": "පිළිගැනීමේ සහ කැපවීමේ චිකිත්සාව (ACT) මගින් බැඳීම් (Cognitive Fusion) ලිහිල් කිරීමට දරන උත්සාහයට සමානය."
        },
        "neuroscientific_analysis": {
            "brain_networks_involved": [
                "Default Mode Network (DMN) පාලනය",
                "Prefrontal Cortex (විධායක පාලනය)"
            ],
            "neuroplasticity_and_habit": "සතිය (Mindfulness) පුහුණු කිරීම හරහා 'එක් දැවිය' වැනි ඒකීය අවධානයක් ගොඩනැගීමෙන් මොළයේ ස්වයංක්‍රීය කෙලෙස් උත්තේජන (Habit loops) වෙනස් වීම.",
            "stress_reduction_mechanism": "කෙලෙස් බැඳුම් ප්‍රහීණ වීම හරහා Amygdala හි අධි-ප්‍රතිචාරී බව අඩුවී, කෝටිසෝල් (Cortisol) මට්ටම අවම වීමෙන් මානසික පීඩනය (Suffering) නැති වීම."
        },
        "cognitive_mechanisms": [
            "සංකේතාත්මක චින්තනය (Symbolic Thinking)",
            "සති සම්පන්න බව (Mindfulness)",
            "විමුක්ති ප්‍රඥාව (Liberating Wisdom)"
        ],
        "emotional_tone": {
            "primary_emotion": "ශාන්තිය (Serenity)",
            "emotional_intensity": 4,
            "emotional_arc": "විමතියේ සිට ප්‍රඥාමය ප්‍රීතිය දක්වා (From Inquiry to Wisdom-based Joy)",
            "mood_keywords": [
                "නිවුණු",
                "ප්‍රඥාවන්ත",
                "ගැඹුරු"
            ]
        },
        "scientific_parallels": [
            {
                "field": "මනෝවිද්‍යාව (Psychology)",
                "theory_name": "අන්වර්ථ රූපක චිකිත්සාව (Metaphorical Cognitive Restructuring)",
                "parallel_description": "සංකීර්ණ මානසික සංකල්ප සරල භෞතික රූපක (රථය) හරහා වටහා ගැනීම මගින් අවබෝධය පහසු කිරීම.",
                "confidence_score": 4
            }
        ],
        "sutta_connections": [
            {
                "shared_concept": "රථ උපමාව (The Chariot Metaphor)",
                "related_teachings": [
                    "වජිරා සූත්‍රය (Vajira Sutta)"
                ],
                "connection_type": "ධර්ම කරුණු පැහැදිලි කිරීම සඳහා යොදාගත් සමාන උපමා"
            }
        ],
        "practical_takeaway_sinhala": "ඔබේ ශරීරය යනු නිරන්තරයෙන් වෙනස් වන, ආහාරයෙන් යැපෙන රථයක් වැනි දෙයක් බව වටහාගෙන, සතිය සහ ශීලය මගින් මානසික නිදහස ලබා ගන්න.",
        "daily_practice_steps": [
            "දිනපතා මොහොතක් පාසා සිරුරේ අනිත්‍ය බව මෙනෙහි කරන්න.",
            "සිතේ රාගය හෝ ද්වේෂය ඇතිවන විට ඒවා 'බැඳුම්' ලෙස හඳුනාගෙන බැහැර කරන්න.",
            "ඕනෑම කාර්යයකදී සති සම්පන්න බව (එක් දැවිය) පවත්වා ගැනීමට උත්සාහ කරන්න."
        ]
    },
    "content": [
        {
            "pali": "ඒකං සමයං ආයස්මා කාමභූ මච්ඡිකාසණ්ඩේ විහරති අම්බාටකවනේ. අථ ඛෝ චිත්තෝ ගහපති යේනායස්මා කාමභූ තේනුපසංකමි, උපසංකමිත්වා ආයස්මන්තං කාමභුං අභිවාදෙත්වා ඒකමන්තං නිසීදි. ඒකමන්තං නිසින්නං ඛෝ චිත්තං ගහපතිං ආයස්මා කාමභූ ඒතදවෝච: වුත්තමිදං ගහපති:",
            "sinhala": "ඒ දිනවල ආයුෂ්මත් කාමභූ තෙරුන් වහන්සේ වැඩසිටියේ මච්ඡිකාසණ්ඩයේ අම්බාටක වනයේ. එදා චිත්ත ගෘහපතිතුමා, ආයුෂ්මත් කාමභූ තෙරුන් වහන්සේ වැඩසිටි තැනට පැමිණුනා. පැමිණිලා ආයුෂ්මත් කාමභූ තෙරුන් වහන්සේට ආදරයෙන් වන්දනා කොට එකත්පස්ව වාඩිවුණා. එකත්පස්ව වාඩිවුණ චිත්ත ගෘහපතිතුමා හට ආයුෂ්මත් කාමභූ තෙරුන් වහන්සේ මෙකරුණ පැවසුවා. “ගෘහපතිය, භාග්‍යවතුන් වහන්සේ මෙය වදාරලා තියෙනවා."
        },
        {
            "pali": "නේලංගෝ සේතපච්ඡාදෝ ඒකාරෝ වත්තතී රථෝ\nඅනීඝං පස්ස ආයන්තං ඡින්නසෝතං අබන්ධනන්ති",
            "sinhala": "‘රථයක් තියෙනවා. දොස් රහිතයි. සුදු වැස්මකින් යුක්තයි. එක් දැවියකින් යුක්තයි. දුක් නැති සිඳුණු සැඩපහර ඇති බැඳුම් රහිතව එන ඒ රථය දෙස බලන්න.’"
        },
        {
            "pali": "ඉමස්ස නු ඛෝ ගහපති සංඛිත්තේන භාසිතස්ස කථං විත්ථාරේන අත්ථෝ දට්ඨබ්බෝති? කින්නු ඛෝ ඒතං භන්තේ භගවතා භාසිතන්ති? ඒවං ගහපතීති. තේන හි භන්තේ මුහුත්තං ආගමේහි යාවස්ස අත්ථං පෙක්ඛාමීති. අථ ඛෝ චිත්තෝ ගහපති මුහුත්තං තුණ්හී හුත්වා ආයස්මන්තං කාමභුං ඒතදවෝච:",
            "sinhala": "පින්වත් ගෘහපතිය, සංක්ෂේපයෙන් වදාරණ ලද මේ දේශනාවෙහි අර්ථය විස්තර වශයෙන් දැන ගත යුත්තේ කොහොමද?” “ස්වාමීනී, කිම ඔය දෙසුම භාග්‍යවතුන් වහන්සේ විසින් වදාරණ ලද දෙයක්ද?” “එසේය ගෘහපතිතුමනි.” “එසේ වී නම් ස්වාමීනී, මං අර්ථය නුවණින් විමසා බලනකල් මොහොතක් ඉවසනු මැනව.” ඉතින් චිත්ත ගෘහපතිතුමා මොහොතක් නිශ්ශබ්දව ඉඳලා ආයුෂ්මත් කාමභූ තෙරුන්ට මෙහෙම කිව්වා."
        },
        {
            "pali": "නේලංගන්ති ඛෝ භන්තේ සීලානමේතං අධිවචනං. සේතපච්ඡාදෝති ඛෝ භන්තේ විමුත්තියා ඒතං අධිවචනං. ඒකාරෝති ඛෝ භන්තේ සතියා ඒතං අධිවචනං. වත්තතීති ඛෝ භන්තේ අභික්කමපටික්කමස්සේතං අධිවචනං. රථෝති ඛෝ භන්තේ ඉමස්සේතං චාතුමහාභූතිකස්ස කායස්ස අධිවචනං මාතාපෙත්තිකසම්භවස්ස ඕදනකුම්මාසූපචයස්ස අනිච්චුච්ඡාදන පරිමද්දන භේදන විද්ධංසන ධම්මස්ස. රාගෝ ඛෝ භන්තේ නීඝෝ දෝසෝ නීඝෝ මෝහෝ නීඝෝ. තේ ඛීණාසවස්ස භික්ඛුනෝ පහීනා උච්ඡින්නමූලා තාලාවත්ථුකතා අනභාවකතා ආයතිං අනුප්පාදධම්මා. තස්මා ඛීණාසවෝ භික්ඛු අනීඝෝති වුච්චති. ආයන්තන්ති ඛෝ භන්තේ අරහතෝ ඒතං අධිවචනං. සෝතෝති ඛෝ භන්තේ තණ්හාය ඒතං අධිවචනං. සා ඛීණාසවස්ස භික්ඛුනෝ පහීනා උච්ඡින්නමූලා තාලාවත්ථුකතා අනභාවකතා ආයතිං අනුප්පාදධම්මා. තස්මා ඛීණාසවෝ භික්ඛු ඡින්නසෝතෝති වුච්චති. රාගෝ ඛෝ භන්තේ බන්ධනං, දෝසෝ බන්ධනං, මෝහෝ බන්ධනං. තේ ඛීණාසවස්ස භික්ඛුනෝ පහීනා උච්ඡින්නමූලා තාලාවත්ථුකතා අනභාවකතා ආයතිං අනුප්පාදධම්මා. තස්මා ඛීණාසවෝ භික්ඛු අබන්ධනෝති වුච්චති. ඉති ඛෝ භන්තේ යන්තං වුත්තං භගවතා:",
            "sinhala": "“ස්වාමීනී, නේලංග (දොස් රහිත) කියලා කිව්වේ මේ සීලයට කියන නමක්. ස්වාමීනී, සේතපච්ඡාදෝ (සුදු වැස්මක්) කියලා කිව්වේ විමුක්තියට කියන නමක්. ස්වාමීනී, ඒකාර (එක් දැවියක්) කියලා කිව්වේ සිහියට කියන නමක්. ස්වාමීනී, වත්තති (තියෙනවා) කියලා කිව්වේ ඉදිරිය බලා යෑමත් ආපසු හැරී ඒමත් යන මෙයට කියන නමක්. ස්වාමීනී, රථ (රථය) කියලා කිව්වේ මව්පියන්ගෙන් හටගත්, බත් වෑංජන වලින් වැඩෙන, අනිත්‍ය වූ, ඉලීම් පිරිමැදීම් කරමින් නඩත්තු වෙන, බිඳෙන සුළු, වැනසෙන සුළු, සතර මහා භූතයන්ගෙන් හටගත් මේ කයට කියන නමක්. ස්වාමීනී, රාගය යනු (නීඝ) දුකකි. ද්වේෂය යනු (නීඝ) දුකකි. මෝහය යනු (නීඝ) දුකකි. ඒවා ක්ෂීණාශ්‍රව වූ රහත් භික්ෂුවට ප්‍රහීණ වෙලයි තියෙන්නේ. මුලින්ම ඉදිරිලයි තියෙන්නේ. මුදුන සිඳුනු තල් ගසක් මෙන් වෙලයි තියෙන්නේ. අභාවයට පත්වෙලයි තියෙන්නේ. නැවත නූපදිනා ස්වභාවයෙන් යුක්තවයි තියෙන්නේ. ඒ නිසයි අරහත් භික්ෂුවට අනීඝ (දුක් නෑ) කියලා කියන්නේ. ස්වාමීනී, ආයන්ත (පැමිණෙන කෙනා) කියලා කියන්නේ රහතන් වහන්සේට කියන නමක්. ස්වාමීනී, සෝත (සැඩපහර) කියලා කියන්නේ මේ තණ්හාවට කියන නමක්. එය ක්ෂීණාශ්‍රව වූ රහත් භික්ෂුවට ප්‍රහීණ වෙලයි තියෙන්නේ. මුලින්ම ඉදිරිලයි තියෙන්නේ. මුදුන සිඳුන තල්ගසක් මෙන් වෙලයි තියෙන්නේ. අභාවයට පත්වෙලයි තියෙන්නේ. නැවත නූපදිනා ස්වභාවයෙන් යුක්තවයි තියෙන්නේ. ඒ නිසා රහතන් වහන්සේටයි ඡින්නසෝත (සැඩපහර සිඳින ලද කෙනා) කියලා කියන්නේ. ස්වාමීනී, රාගය යනු බන්ධනයකි. ද්වේෂය යනු බන්ධනයකි. මෝහය යනු බන්ධනයකි. ඒවා ක්ෂීණාශ්‍රව වූ රහත් භික්ෂුවට ප්‍රහීණ වෙලයි තියෙන්නේ. මුලින්ම ඉදිරිලයි තියෙන්නේ. මුදුන සිඳුන තල්ගසක් මෙන් වෙලයි තියෙන්නේ. අභාවයට පත්වෙලයි තියෙන්නේ. නැවත නූපදිනා ස්වභාවයෙන් යුක්තවයි තියෙන්නේ. ඒ නිසා අරහත් භික්ෂුවට අබන්ධන (බැඳුම් නෑ) කියලා කියනවා. ස්වාමීනී, මෙසේ භාග්‍යවතුන් වහන්සේ ඒ යම් දෙයක් වදාරණ ලද්දේ ද,"
        },
        {
            "pali": "“නේලංගෝ සේතපච්ඡාදෝ ඒකාරෝ වත්තතී රථෝ\nඅනීඝං පස්ස ආයන්තං ඡින්නසෝතං අබන්ධන”න්ති",
            "sinhala": "‘රථයක් තියෙනවා. දොස් රහිතයි. සුදු වැස්මකින් යුක්තයි. එක් දැවියකින් යුක්තයි. දුක් නැති සිඳුණු සැඩපහර ඇති බැඳුම් රහිතව එන ඒ රථය දෙස බලන්න.’"
        },
        {
            "pali": "ඉමස්ස ඛ්වාහං භන්තේ භගවතා සංඛිත්තේන භාසිතස්ස ඒවං විත්ථාරේන අත්ථං ආජානාමීති. ලාභා තේ ගහපති, සුලද්ධන්තේ ගහපති, යස්ස තේ ගම්භීරේ බුද්ධවචනේ පඤ්ඤාචක්ඛු කමතීති.",
            "sinhala": "ස්වාමීනී, භාග්‍යවතුන් වහන්සේ විසින් සංක්ෂේපයෙන් වදාරණ ලද මෙම දේශනාවෙහි අර්ථය ඔය ආකාරයෙනුයි විස්තර වශයෙන් මට තේරුණේ.” “පින්වත් ගෘහපතිය, ඔබට ලාභයක් ම යි. පින්වත් ගෘහපතිය, ඔබට සොඳුරු ලාභයක් ම යි. ගම්භීර වූ බුද්ධ වචනය පිළිබඳව ඒ ඔබට ප්‍රඥා ඇස තියෙනවා.”"
        }
    ]
}