{
    "nikaya": "මහා වග්ගෝ",
    "vagga": "පොක්ඛරණී සුත්තං",
    "sutta_title": "පොකුණ උපමාවට ගෙන වදාළ දෙසුම",
    "id": "6242",
    "discovery_content": {
        "is_deep_meaning_found": true,
        "theme_category": "චතුරාර්ය සත්‍ය අවබෝධය සහ දුක ක්ෂය කිරීම",
        "complexity_rating": 3,
        "analysis_confidence": 100,
        "short_summary": "චතුරාර්ය සත්‍යය අවබෝධ කරගත් ආර්ය ශ්‍රාවකයා විඳ අවසන් කළ දුක මහා පොකුණක ජලයට සමාන වන අතර, ඉතිරිව ඇති දුක තණ අග රැඳි පිනි බිඳක් සේ අල්පය.",
        "long_summary": "පනස් යොදුන් දිග, පළල සහ ගැඹුර ඇති මහා පොකුණක ජල ප්‍රමාණයට සාපේක්ෂව කුස තණ අග රැඳි ජල බිඳක් කොතරම් සුළු ද, එලෙසම චතුරාර්ය සත්‍යය අවබෝධ කරගත් පුද්ගලයා විසින් ක්ෂය කරන ලද දුක අතිමහත්ය. ඔහුට තවදුරටත් අත්විඳීමට ඉතිරිව ඇත්තේ සංසාරික දුක හා සසඳන කල අතිශය සුළු කොටසකි. දුක, දුකේ හටගැනීම, දුක නිරුද්ධ වීම සහ එයට මග යන සතර සත්‍යයන් අවබෝධ කරගැනීම සඳහා වීර්යය වැඩිය යුතු බව මෙහි අවධාරණය කෙරේ.",
        "main_discovery": "චතුරාර්ය සත්‍යය අවබෝධ කරගත් ආර්ය ශ්‍රාවකයා සතු ඉතිරිව ඇති දුක, මහා පොකුණක ජලයට සාපේක්ෂව තණ අග රැඳි ජල බිඳක් තරම් අල්ප බව.",
        "core_truth_of_sutta": "චතුරාර්ය සත්‍යය අවබෝධය (Sotapanna state and beyond) මගින් සත්වයා අත්විඳිය යුතු අතිමහත් දුක්ඛස්කන්ධයෙන් නිදහස් කරන අතර ඉතිරි වන්නේ අතිශය සීමිත දුකක් පමණි.",
        "path_to_nibbana": {
            "doctrinal_meaning": "සෝවාන් ආදී මාර්ගඵල අවබෝධයත් සමඟ සතර අපාය ඇතුළු අතිමහත් දුක ක්ෂය වීම.",
            "how_it_aids_liberation": "සංසාරික පැවැත්මේ බියකරු බව හා සසඳන කල මගඵල ලාභියා ලබන ආරක්ෂාව පෙන්වා දී වීර්යය ඇති කිරීම මගින්.",
            "practical_renunciation": "දුකේ මූලය (සමුදය) හඳුනාගෙන අවබෝධයෙන් යුතුව උපාදානයන් අත්හැරීම."
        },
        "psychological_analysis": {
            "mental_states_analyzed": [
                "අවබෝධය (Insight)",
                "වීර්යය (Effort)",
                "සංවේගය (Urgency)"
            ],
            "cognitive_impact": "යථාර්ථය පිළිබඳව ඇති වන නිවැරදි දැක්ම (Right View) මගින් අනාගතය පිළිබඳ පවතින අතාර්කික බිය (Existential Anxiety) දුරු කරයි.",
            "modern_psychology_parallel": "Acceptance and Commitment Therapy (ACT) හි එන 'Values Clarification' සහ 'Diffusion' ක්‍රියාවලිය හරහා ගැටලුවල බැරෑරුම්කම නිවැරදිව තක්සේරු කිරීම."
        },
        "neuroscientific_analysis": {
            "brain_networks_involved": [
                "Default Mode Network (DMN)",
                "Amygdala",
                "Anterior Cingulate Cortex (ACC)"
            ],
            "neuroplasticity_and_habit": "ධර්ම අවබෝධය හරහා මමත්වය ගොඩනගන DMN ජාලයේ ක්‍රියාකාරිත්වය අඩුවීමෙන්, පැරණි සංස්කාර (Habitual patterns) ක්ෂය වී නව ස්නායුක පථ නිර්මාණය වේ.",
            "stress_reduction_mechanism": "අවබෝධය හරහා Amygdala හි අධික්‍රියාකාරිත්වය (Fear response) පාලනය වී Cortisol මට්ටම අඩු වීමෙන් මානසික ස්ථාවරත්වය ඇති වේ."
        },
        "cognitive_mechanisms": [
            "Cognitive Restructuring",
            "Perspective Shifting",
            "Perceptual Scaling"
        ],
        "emotional_tone": {
            "primary_emotion": "සැනසීම (Relief)",
            "emotional_intensity": 9,
            "emotional_arc": "අතිමහත් පීඩනයක සිට (මහා පොකුණ) අතිශය සැහැල්ලුව දක්වා (තණ අග ජල බිඳ)",
            "mood_keywords": [
                "අභිප්‍රේරණය",
                "නිසැකබව",
                "සැහැල්ලුව"
            ]
        },
        "scientific_parallels": [
            {
                "field": "Psychology",
                "theory_name": "Cognitive Reframing",
                "parallel_description": "අර්බුදයක සමස්ත ව්‍යුහය අවබෝධ කර ගැනීමෙන් පසුව, විසඳීමට ඉතිරිව ඇති කොටස පිළිබඳව ඇති වන මානසික බිය පහව යාම.",
                "confidence_score": 90
            }
        ],
        "sutta_connections": [
            {
                "shared_concept": "දුක්ඛක්ඛය (Cessation of Suffering)",
                "related_teachings": [
                    "ධම්මචක්කප්පවත්තන සූත්‍රය",
                    "නඛසිඛා සූත්‍රය"
                ],
                "connection_type": "Comparative Analogy"
            }
        ],
        "practical_takeaway_sinhala": "ජීවිතයේ ප්‍රශ්න දෙස බලන ආකාරය වෙනස් කරන්න; චතුරාර්ය සත්‍යය අවබෝධ කරගැනීමෙන් මහා පීඩනයකින් නිදහස් විය හැකි බව වටහාගෙන එම මාවතේ වීර්යයෙන් කටයුතු කරන්න.",
        "daily_practice_steps": [
            "ජීවිතයේ අත්විඳින පීඩාවන් 'දුක' ලෙස හඳුනාගෙන එයට හේතුව තණ්හාව බව විමසන්න.",
            "සෑම පීඩාකාරී අවස්ථාවකදීම මෙය 'අනිත්‍ය' බව සිහිපත් කරමින් මනස පුහුණු කරන්න.",
            "සතර සත්‍යය පිළිබඳ කියවීම සහ ශ්‍රවණය මගින් සම්මා දිට්ඨිය දියුණු කරගන්න."
        ]
    },
    "content": [
        {
            "pali": "සෙය්‍යථාපි භික්ඛවේ, පොක්ඛරණී පඤ්ඤාස යෝජනානි ආයාමේන, පඤ්ඤාස යෝජනානි විත්ථාරේන, පඤ්ඤාස යෝජනානි උබ්බේධේන, පුණ්ණා උදකස්ස සමතිත්තිකා කාකපෙය්‍යා. තතෝ පුරිසෝ කුසග්ගේන උදකං උද්ධරෙය්‍ය. තං කිං මඤ්ඤථ භික්ඛවේ, කතමං නු ඛෝ බහුතරං, යං වා කුසග්ගේන උබ්භතං, යං වා පොක්ඛරණියා උදකන්ති? ඒතදේව භන්තේ, බහුතරං යදිදං පොක්ඛරණියා උදකං. අප්පමත්තකං කුසග්ගේන උදකං උබ්භතං. සංඛම්පි න උපේති, උපනිධිම්පි න උපේති, කලභාගම්පි න උපේති පොක්ඛරණියා උදකං උපනිධාය කුසග්ගේන උදකං උබ්භතන්ති. ඒවමේව ඛෝ භික්ඛවේ, අරියසාවකස්ස ....(පෙ).... යෝගෝ කරණීයෝති.",
            "sinhala": "“මහණෙනි, එය මෙබඳු දෙයකි. පනස් යොදුන් පළල, පනස් යොදුන් දිග, පනස් යොදුන් ගැඹුරු ජලයෙන් පිරී ගිය, ඉවුර දක්වා පිරීගිය, කපුටන්ට ද පහසුවෙන් පානය කළ හැකි පරිදි වූ පොකුණක් ඇත්තේ ය. පුරුෂයෙක් කුස තණ අගින් එයින් දිය ස්වල්පයක් බැහැරට ගන්නේ ය."
        }
    ]
}