{
    "nikaya": "මහා වග්ගෝ",
    "vagga": "අනුසය සුත්තං",
    "sutta_title": "අනුසය ගැන වදාළ දෙසුම",
    "id": "7048",
    "discovery_content": {
        "is_deep_meaning_found": true,
        "theme_category": "සමාධි භාවනා සහ අනුසය ප්‍රහාණය (Concentration and Eradication of Latent Tendencies)",
        "complexity_rating": 7,
        "analysis_confidence": 95,
        "short_summary": "ආනාපානසති සමාධිය පදනම් කරගෙන මනසෙහි පවතින අකුසල අනුසය සහ විපත්තිකාරී චේතනා මුලින්ම නැසීමට මඟ පෙන්වන දේශනාවකි.",
        "long_summary": "මෙම දේශනය මගින් ආනාපානසති භාවනාව තුළින් ගොඩනැගෙන සමාධිය, මනසෙහි ඇති සියලු කෙලෙස් නැසීමේ ආරම්භක පදනම ලෙස විස්තර කරයි. ආශ්වාස ප්‍රාශ්වාසය කෙරෙහි අවධානය යොමු කිරීමෙන් මනසෙහි ඇතිවන චංචල ස්වභාවය පාලනය කරගත හැකි අතර, එමගින් කාමයන්, අකුසල චේතනා සහ භයානක මනෝභාවයන් (අනුසය) ක්‍රමයෙන් ක්ෂය කිරීමට අවශ්‍ය මානසික ශක්තිය සහ ඒකාග්‍රතාවය ගොඩනැගෙන ආකාරය මෙහි අවධාරණය කෙරේ.",
        "main_discovery": "ආනාපානසති සමාධිය (Anapanasati Samadhi) මගින් සිතේ ගැඹුරින් සැඟවී ඇති අනුසය කෙලෙස් (Latent Tendencies) නැසීමේ ක්‍රියාවලිය ආරම්භ කිරීමේ මූලික පදනම සකස් කරයි.",
        "core_truth_of_sutta": "ගැඹුරු මානසික ඒකාග්‍රතාවය (සමාධිය) තුළින් පමණක් මනසෙහි සැඟවී ඇති සියුම් අකුසල සහජාසයන් (අනුසය) මුලිනුපුටා දැමිය හැකිය.",
        "path_to_nibbana": {
            "doctrinal_meaning": "අනුසය කෙලෙස් නැසීම (Eradication of Anusaya).",
            "how_it_aids_liberation": "ආනාපානසති සමාධිය මගින් කෙලෙස් වලට නැවත මතු වීමට ඇති ඉඩකඩ (අනුසය) අහුරා දමමින් සිත පූර්ණ විමුක්තිය කරා යොමු කරයි.",
            "practical_renunciation": "ආශ්වාස ප්‍රාශ්වාසය කෙරෙහි අවධානය තබා ගනිමින් අන් සියලු බාහිර අරමුණු සහ අකුසල සංස්කාර අත්හැරීම."
        },
        "psychological_analysis": {
            "mental_states_analyzed": [
                "කාමය (Desire)",
                "අකුසල චේතනා (Unwholesome Intentions)",
                "සමාධිය (Concentration)"
            ],
            "cognitive_impact": "සිතෙහි ඇතිවන විචලනයන් (Cognitive Oscillations) අවම කරමින් ප්‍රජානන ස්ථාවරත්වය ඇති කරයි.",
            "modern_psychology_parallel": "Mindfulness-Based Stress Reduction (MBSR) සහ මනෝවිශ්ලේෂණයේදී යටිසිතේ පවතින බලපෑම් (Unconscious biases) හඳුනාගැනීමේ ක්‍රියාවලියට සමාන වේ."
        },
        "neuroscientific_analysis": {
            "brain_networks_involved": [
                "Default Mode Network (DMN)",
                "Task-Positive Network (TPN)",
                "Prefrontal Cortex"
            ],
            "neuroplasticity_and_habit": "ආශ්වාසය කෙරෙහි අවධානය පුහුණු කිරීමේදී (Neuroplasticity), නිරන්තරයෙන් අකුසලයට යොමුවන මොළයේ ස්නායුක මාර්ග දුර්වල වී ඒකාග්‍රතාවයට අදාළ මාර්ග ශක්තිමත් වේ.",
            "stress_reduction_mechanism": "හුස්ම කෙරෙහි අවධානය යොමු කිරීමෙන් Amygdala හි ක්‍රියාකාරීත්වය අඩු වී ආතති හෝමෝන (Cortisol) පාලනය වෙමින් භීතිය සහ ආවේග පාලනය වේ."
        },
        "cognitive_mechanisms": [
            "සතිමත්බව (Mindfulness)",
            "ඒකාග්‍රතාවය (Focusing)",
            "සංස්කාර නිරෝධය (Cessation of Formations)",
            "චේතනා පාලනය (Volitional Control)"
        ],
        "emotional_tone": {
            "primary_emotion": "උපේක්ෂාව (Equanimity)",
            "emotional_intensity": 8,
            "emotional_arc": "අසන්සුන් මනසක සිට විවේකී ඒකාග්‍රතාවයකට පත්වීම (Agitated to Focused Calm)",
            "mood_keywords": [
                "ශාන්ත",
                "ප්‍රසන්න",
                "නිරවුල්",
                "ස්ථාවර"
            ]
        },
        "scientific_parallels": [
            {
                "field": "Cognitive Science",
                "theory_name": "Attentional Control Theory",
                "parallel_description": "ආශ්වාස ප්‍රාශ්වාසය කෙරෙහි අවධානය යොමු කිරීමෙන් මනසෙහි අවධානය වෙනතකට යොමු කරන බාහිර උත්තේජන (Distractors) පාලනය කරමින් වැඩකාරී මතකය (Working Memory) කළමනාකරණය කිරීම.",
                "confidence_score": 90
            }
        ],
        "sutta_connections": [
            {
                "shared_concept": "අනුසය ප්‍රහාණය (Elimination of Latent Tendencies)",
                "related_teachings": [
                    "ආනාපානසති සූත්‍රය (Anapanasati Sutta)",
                    "මධුපිණ්ඩික සූත්‍රය (Madhupindika Sutta)"
                ],
                "connection_type": "යාන්ත්‍රික සමානතාව (Methodological Similarity)"
            }
        ],
        "practical_takeaway_sinhala": "නිරතුරුව තමාගේ හුස්ම පිළිබඳව අවධානයෙන් සිටීමෙන් සිතේ ඇතිවන ක්ෂණික කෝපය හෝ ආශාවන් පාලනය කරගෙන මානසික නිදහස ලබා ගත හැක.",
        "daily_practice_steps": [
            "දිනකට අවම වශයෙන් විනාඩි 10-15ක් නිහඬව වාඩි වී හුස්ම දෙස බලා සිටින්න.",
            "සිත වෙනත් අතකට යන සෑම විටම මෘදු ලෙස නැවත හුස්ම වෙත අවධානය යොමු කරන්න.",
            "නරක සිතුවිල්ලක් උපදින විට එය පසුපස නොගොස් හුස්ම ගැන සිතමින් එය අත හරින්න."
        ]
    },
    "content": [
        {
            "pali": "ආනාපානසතිසමාධි භික්ඛවේ ....(පෙ).... අනුසයසමුග්ඝාතාය සංවත්තතීති.",
            "sinhala": "මහණෙනි, ආනාපානසති සමාධිය ….(පෙ)…. කෙලෙස් අනුසය මුලින් ම නැසීම පිණිස පවතියි."
        }
    ]
}